README.md
setup.py
PySGP30.egg-info/PKG-INFO
PySGP30.egg-info/SOURCES.txt
PySGP30.egg-info/dependency_links.txt
PySGP30.egg-info/requires.txt
PySGP30.egg-info/top_level.txt
sgp30/__init__.py
sgp30/crc.py
sgp30/sgp30.py
tests/__init__.py
tests/context.py
tests/mock_smbus2.py
tests/test_crc.py
tests/test_sgp.py