Metadata-Version: 2.1
Name: PySGP30
Version: 0.1.8
Summary: Library for reading data from the Sensirion SGP30
Home-page: https://github.com/Conr86/PySGP30
Author: Connor Kneebone
Author-email: connor@sfxrescue.com
License: MIT
Keywords: sgp30 i2c smbus smbus2
Platform: UNKNOWN
Classifier: Development Status :: 4 - Beta
Classifier: Intended Audience :: Developers
Classifier: License :: OSI Approved :: MIT License
Classifier: Programming Language :: Python :: 2
Classifier: Programming Language :: Python :: 2.7
Classifier: Programming Language :: Python :: 3
Classifier: Programming Language :: Python :: 3.4
